Quantum_Correlations_Visualized/Quantum_Correlations_Visualized.py
Quantum_Correlations_Visualized/__init__.py
quantum_correlations_visualized-0.1.13.dist-info/entry_points.txt
quantum_correlations_visualized-0.1.13.dist-info/WHEEL
quantum_correlations_visualized-0.1.13.dist-info/METADATA
quantum_correlations_visualized-0.1.13.dist-info/RECORD
