Metadata-Version: 2.1
Name: Quantum-Correlations-Visualized
Version: 0.1.13
Summary: Visual Simulation of a Two-Channel Quantum Bell Test Experiment
Author-email: Barry Schwartz <sortsmill@crudfactory.com>
Requires-Python: >=3.11
Classifier: Programming Language :: Python :: 3
Classifier: License :: OSI Approved :: The Unlicense (Unlicense)
Classifier: Operating System :: POSIX
Classifier: Intended Audience :: Science/Research
Classifier: Topic :: Scientific/Engineering :: Visualization
Classifier: Topic :: Scientific/Engineering :: Physics
Classifier: Environment :: X11 Applications
Classifier: Natural Language :: English
Requires-Dist: pyglet >= 2.0.9
Project-URL: Author-on-Mastodon, https://masto.ai/@chemoelectric
Project-URL: Homepage, https://github.com/chemoelectric/eprb_signal_correlations
